YehuoRtThreadNeiheShixianYuYingyongKaifaShizhan/README.md
YehuoRtThreadNeiheShixianYuYingyongKaifaShizhan/__init__.py
YehuoRtThreadNeiheShixianYuYingyongKaifaShizhan/__main__.py
YehuoRtThreadNeiheShixianYuYingyongKaifaShizhan/file.epub
YehuoRtThreadNeiheShixianYuYingyongKaifaShizhan/index.html
YehuoRtThreadNeiheShixianYuYingyongKaifaShizhan/css/__init__.py
YehuoRtThreadNeiheShixianYuYingyongKaifaShizhan/css/annotations.css
YehuoRtThreadNeiheShixianYuYingyongKaifaShizhan/css/main.css
YehuoRtThreadNeiheShixianYuYingyongKaifaShizhan/css/normalize.css
YehuoRtThreadNeiheShixianYuYingyongKaifaShizhan/css/popup.css
YehuoRtThreadNeiheShixianYuYingyongKaifaShizhan/font/__init__.py
YehuoRtThreadNeiheShixianYuYingyongKaifaShizhan/font/fontello.eot
YehuoRtThreadNeiheShixianYuYingyongKaifaShizhan/font/fontello.svg
YehuoRtThreadNeiheShixianYuYingyongKaifaShizhan/font/fontello.ttf
YehuoRtThreadNeiheShixianYuYingyongKaifaShizhan/font/fontello.woff
YehuoRtThreadNeiheShixianYuYingyongKaifaShizhan/img/__init__.py
YehuoRtThreadNeiheShixianYuYingyongKaifaShizhan/img/annotator-glyph-sprite.png
YehuoRtThreadNeiheShixianYuYingyongKaifaShizhan/img/annotator-icon-sprite.png
YehuoRtThreadNeiheShixianYuYingyongKaifaShizhan/img/apple-touch-icon.png
YehuoRtThreadNeiheShixianYuYingyongKaifaShizhan/img/cancelfullscreen.png
YehuoRtThreadNeiheShixianYuYingyongKaifaShizhan/img/close.png
YehuoRtThreadNeiheShixianYuYingyongKaifaShizhan/img/fullscreen.png
YehuoRtThreadNeiheShixianYuYingyongKaifaShizhan/img/loader.gif
YehuoRtThreadNeiheShixianYuYingyongKaifaShizhan/img/menu-icon.png
YehuoRtThreadNeiheShixianYuYingyongKaifaShizhan/img/save.png
YehuoRtThreadNeiheShixianYuYingyongKaifaShizhan/img/saved.png
YehuoRtThreadNeiheShixianYuYingyongKaifaShizhan/img/settings-s.png
YehuoRtThreadNeiheShixianYuYingyongKaifaShizhan/img/settings.png
YehuoRtThreadNeiheShixianYuYingyongKaifaShizhan/img/star.png
YehuoRtThreadNeiheShixianYuYingyongKaifaShizhan/js/__init__.py
yehuo_rt_thread_neihe_shixian_yu_yingyong_kaifa_shizhan-2024.3.5.0.dist-info/METADATA
yehuo_rt_thread_neihe_shixian_yu_yingyong_kaifa_shizhan-2024.3.5.0.dist-info/WHEEL
yehuo_rt_thread_neihe_shixian_yu_yingyong_kaifa_shizhan-2024.3.5.0.dist-info/entry_points.txt
yehuo_rt_thread_neihe_shixian_yu_yingyong_kaifa_shizhan-2024.3.5.0.dist-info/top_level.txt
yehuo_rt_thread_neihe_shixian_yu_yingyong_kaifa_shizhan-2024.3.5.0.dist-info/RECORD
